geolocaltime/__init__.py
geolocaltime/services.py
geolocaltime/types.py
geolocaltime-0.1.dist-info/licenses/LICENSE
geolocaltime-0.1.dist-info/METADATA
geolocaltime-0.1.dist-info/WHEEL
geolocaltime-0.1.dist-info/top_level.txt
geolocaltime-0.1.dist-info/RECORD
