Metadata-Version: 2.4
Name: geolocaltime
Version: 0.1
Summary: Accurately enriches location data with local time and time-of-day insights.
Project-URL: Homepage, https://geospatial-ai.de
Project-URL: GitHub, https://github.com/Geospatial-AI-DE/geolocaltime-py
Project-URL: Documentation, https://geolocaltime.readthedocs.io/en/latest
Keywords: geospatial,intelligence,time
Classifier: Programming Language :: Python :: 3
Classifier: License :: OSI Approved :: Apache Software License
Classifier: Operating System :: OS Independent
Requires-Python: >=3.7
License-File: LICENSE
Requires-Dist: georapid
Dynamic: license-file
